CHANGES.rst
CONTRIBUTORS.rst
MANIFEST.in
README.rst
bootstrap.py
buildout.cfg
setup.py
cpskin/__init__.py
cpskin.diazotheme.spirit.egg-info/PKG-INFO
cpskin.diazotheme.spirit.egg-info/SOURCES.txt
cpskin.diazotheme.spirit.egg-info/dependency_links.txt
cpskin.diazotheme.spirit.egg-info/entry_points.txt
cpskin.diazotheme.spirit.egg-info/namespace_packages.txt
cpskin.diazotheme.spirit.egg-info/not-zip-safe
cpskin.diazotheme.spirit.egg-info/requires.txt
cpskin.diazotheme.spirit.egg-info/top_level.txt
cpskin/diazotheme/__init__.py
cpskin/diazotheme/spirit/__init__.py
cpskin/diazotheme/spirit/configure.zcml
cpskin/diazotheme/spirit/interfaces.py
cpskin/diazotheme/spirit/profiles.zcml
cpskin/diazotheme/spirit/upgradehandlers.py
cpskin/diazotheme/spirit/profiles/default/browserlayer.xml
cpskin/diazotheme/spirit/profiles/default/cssregistry.xml
cpskin/diazotheme/spirit/profiles/default/jsregistry.xml
cpskin/diazotheme/spirit/profiles/default/lessregistry.xml
cpskin/diazotheme/spirit/profiles/default/metadata.xml
cpskin/diazotheme/spirit/profiles/default/theme.xml
cpskin/diazotheme/spirit/profiles/uninstall/browserlayer.xml
cpskin/diazotheme/spirit/profiles/uninstall/cssregistry.xml
cpskin/diazotheme/spirit/profiles/uninstall/jsregistry.xml
cpskin/diazotheme/spirit/profiles/uninstall/lessregistry.xml
cpskin/diazotheme/spirit/static/manifest.cfg
cpskin/diazotheme/spirit/static/preview.png
cpskin/diazotheme/spirit/static/rules.xml
cpskin/diazotheme/spirit/static/css/styles.css
cpskin/diazotheme/spirit/static/js/cpskin_spirit.js
cpskin/diazotheme/spirit/static/less/liege.less
cpskin/diazotheme/spirit/static/less/minisites.less
cpskin/diazotheme/spirit/static/less/mobile.less
cpskin/diazotheme/spirit/static/less/mobilelarge.less
cpskin/diazotheme/spirit/static/less/producteur.less
cpskin/diazotheme/spirit/static/less/reinventons.less
cpskin/diazotheme/spirit/static/less/styles.less
cpskin/diazotheme/spirit/static/less/variables.less
cpskin/diazotheme/spirit/static/rules/footer.xml
cpskin/diazotheme/spirit/static/rules/header.xml
cpskin/diazotheme/spirit/viewlets/__init__.py
cpskin/diazotheme/spirit/viewlets/banner.py
cpskin/diazotheme/spirit/viewlets/configure.zcml
docs/LICENSE.GPL
docs/LICENSE.rst