Metadata-Version: 1.1
Name: cpskin.diazotheme.spirit
Version: 0.1.47
Summary: Spirit theme for CPSkin
Home-page: https://github.com/IMIO/cpskin.diazotheme.spirit/
Author: IMIO
Author-email: support@imio.be
License: GPL
Keywords: imio cpskin theme
Platform: UNKNOWN
Classifier: Environment :: Web Environment
Classifier: Framework :: Plone
Classifier: Framework :: Plone :: 4.3
Classifier: Programming Language :: Python
Classifier: Programming Language :: Python :: 2.7
